{
  "cab0e4cc_machine_learning_guide.md": {
    "analysis": {},
    "filename": "cab0e4cc_machine_learning_guide.md",
    "metadata": {
      "topic": "machine_learning",
      "type": "markdown"
    },
    "mime_type": "text/markdown",
    "original_name": "machine_learning_guide.md",
    "path": "users/alice/chat_session_20250805_090732_412718/documents/cab0e4cc_machine_learning_guide.md",
    "size": 929,
    "uploaded_at": "2025-08-05T09:07:32.810933",
    "uploaded_by": "alice"
  },
  "e6d1e64e_deep_learning_basics.md": {
    "analysis": {},
    "filename": "e6d1e64e_deep_learning_basics.md",
    "metadata": {
      "topic": "machine_learning",
      "type": "markdown"
    },
    "mime_type": "text/markdown",
    "original_name": "deep_learning_basics.md",
    "path": "users/alice/chat_session_20250805_090732_412718/documents/e6d1e64e_deep_learning_basics.md",
    "size": 861,
    "uploaded_at": "2025-08-05T09:07:32.813744",
    "uploaded_by": "alice"
  }
}